pysenticrypt/__init__.py
pysenticrypt/senticrypt.py
pysenticrypt-0.1.0.dist-info/LICENSE
pysenticrypt-0.1.0.dist-info/METADATA
pysenticrypt-0.1.0.dist-info/WHEEL
pysenticrypt-0.1.0.dist-info/top_level.txt
pysenticrypt-0.1.0.dist-info/RECORD
