Metadata-Version: 2.1
Name: pysenticrypt
Version: 0.1.0
Summary: A simple Python wrapper for the SentiCrypt API.
Home-page: https://github.com/edesaras/pysenticrypt
Author: Aras Edes
Author-email: edesaras@gmail.com
Classifier: Programming Language :: Python :: 3
Classifier: License :: OSI Approved :: MIT License
Classifier: Operating System :: OS Independent
Requires-Python: >=3.6
License-File: LICENSE
Requires-Dist: requests
